rk_mcprotocol/__init__.py
rk_mcprotocol/main.py
rk_mcprotocol-0.0.2.dist-info/METADATA
rk_mcprotocol-0.0.2.dist-info/WHEEL
rk_mcprotocol-0.0.2.dist-info/top_level.txt
rk_mcprotocol-0.0.2.dist-info/RECORD
