Metadata-Version: 2.1
Name: rk_mcprotocol
Version: 0.0.2
